pyroredis/__init__.py
pyroredis/pyroredis.py
pyroredis-0.1.1.dist-info/DESCRIPTION.rst
pyroredis-0.1.1.dist-info/METADATA
pyroredis-0.1.1.dist-info/RECORD
pyroredis-0.1.1.dist-info/WHEEL
pyroredis-0.1.1.dist-info/metadata.json
pyroredis-0.1.1.dist-info/top_level.txt
