Metadata-Version: 2.0
Name: pyroredis
Version: 0.1.1
Summary: Redis backend for Pyrogram session storage 
Home-page: https://github.com/ezdev128/pyrogram-session-redis
Author: Konstantin M.
Author-email: ezdev128@yandex.com
License: MIT
Download-URL: https://github.com/ezdev128/pyrogram-session-redis/releases
Keywords: telegram pyrogram session sessions redis
Platform: UNKNOWN
Classifier: Development Status :: 4 - Beta
Classifier: Intended Audience :: Developers
Classifier: License :: OSI Approved :: MIT License
Classifier: Programming Language :: Python
Classifier: Programming Language :: Python :: 3
Classifier: Programming Language :: Python :: 3.4
Classifier: Programming Language :: Python :: 3.5
Classifier: Programming Language :: Python :: 3.6
Requires-Python: ~=3.4
Requires-Dist: Pyrogram (>=0.6)
Requires-Dist: redis (>=2.0)
